PyColors/__init__.py
PyColors/main.py
pycolortools-0.0.2.dist-info/METADATA
pycolortools-0.0.2.dist-info/WHEEL
pycolortools-0.0.2.dist-info/licenses/LICENSE
pycolortools-0.0.2.dist-info/RECORD
