Metadata-Version: 2.1
Name: PyColorTools
Version: 0.0.2
Summary: A colorfull package
Author: Rayaan khan
License-File: LICENSE
Classifier: License :: OSI Approved :: MIT License
Classifier: Operating System :: OS Independent
Classifier: Programming Language :: Python :: 3
Requires-Python: >3.7
